README
setup.py
snapbill/__init__.py
snapbill/base.py
snapbill/connection.py
snapbill/exceptions.py
snapbill/objects.py
snapbill/util.py
snapbill/xid.py
snapbill.egg-info/PKG-INFO
snapbill.egg-info/SOURCES.txt
snapbill.egg-info/dependency_links.txt
snapbill.egg-info/requires.txt
snapbill.egg-info/top_level.txt
snapbill.egg-info/zip-safe