Metadata-Version: 1.1
Name: snapbill
Version: 0.2.1
Summary: Wrapper for the SnapBill v1 API.
Home-page: https://github.com/snapbill/snapbill-pyapi
Author: Josh Yudaken
Author-email: UNKNOWN
License: UNKNOWN
Download-URL: http://pypi.python.org/pypi/snapbill/
Keywords: snapbill api wrapper
Platform: UNKNOWN
Classifier: Development Status :: 5 - Production/Stable
Classifier: Intended Audience :: Developers
Classifier: License :: OSI Approved :: MIT License
Classifier: Natural Language :: English
Classifier: Operating System :: OS Independent
Classifier: Programming Language :: Python
Classifier: Topic :: Software Development :: Libraries :: Python Modules
